heysamipkg/__init__.py
heysamipkg/saysami.py
heysamipkg-0.0.1.dist-info/LICENSE
heysamipkg-0.0.1.dist-info/METADATA
heysamipkg-0.0.1.dist-info/WHEEL
heysamipkg-0.0.1.dist-info/top_level.txt
heysamipkg-0.0.1.dist-info/RECORD
