Metadata-Version: 2.1
Name: heysamipkg
Version: 0.0.1
Summary: Say hello for samiforgit package.
Home-page: UNKNOWN
Author: Md Samiul Alim
Author-email: <mdsamiul05@gmail.com>
License: UNKNOWN
Keywords: python,print
Platform: UNKNOWN
Classifier: Development Status :: 1 - Planning
Classifier: Intended Audience :: Developers
Classifier: Programming Language :: Python :: 3
Classifier: Operating System :: Unix
Classifier: Operating System :: MacOS :: MacOS X
Classifier: Operating System :: Microsoft :: Windows
